<?xml version="1.0" encoding="UTF-8"?>
<sbml xmlns="http://www.sbml.org/sbml/level3/version2/core" level="3" version="2">
  <model id="biocrnpyler_98682" name="biocrnpyler_98682" substanceUnits="mole" timeUnits="second" volumeUnits="litre" areaUnits="square_metre" lengthUnits="metre" extentUnits="mole">
    <listOfUnitDefinitions>
      <unitDefinition id="square_metre">
        <listOfUnits>
          <unit kind="metre" exponent="2" scale="0" multiplier="1"/>
        </listOfUnits>
      </unitDefinition>
    </listOfUnitDefinitions>
    <listOfCompartments>
      <compartment id="default" name="default" spatialDimensions="3" size="1e-06" constant="true"/>
    </listOfCompartments>
    <listOfSpecies>
      <species id="dna_main_assembly" name="main_assembly" compartment="default" initialConcentration="0" substanceUnits="mole" hasOnlySubstanceUnits="false" boundaryCondition="false" constant="false"/>
      <species id="complex_Ara_2x_AraC_2x_" name="Ara_2x_AraC_2x" compartment="default" initialConcentration="0" substanceUnits="mole" hasOnlySubstanceUnits="false" boundaryCondition="false" constant="false"/>
      <species id="rna_main_assembly" name="main_assembly" compartment="default" initialConcentration="0" substanceUnits="mole" hasOnlySubstanceUnits="false" boundaryCondition="false" constant="false"/>
      <species id="AmtR" name="AmtR" compartment="default" initialConcentration="0" substanceUnits="mole" hasOnlySubstanceUnits="false" boundaryCondition="false" constant="false"/>
      <species id="dna_reporter_assembly" name="reporter_assembly" compartment="default" initialConcentration="0" substanceUnits="mole" hasOnlySubstanceUnits="false" boundaryCondition="false" constant="false"/>
      <species id="rna_reporter_assembly" name="reporter_assembly" compartment="default" initialConcentration="0" substanceUnits="mole" hasOnlySubstanceUnits="false" boundaryCondition="false" constant="false"/>
      <species id="YFP" name="YFP" compartment="default" initialConcentration="0" substanceUnits="mole" hasOnlySubstanceUnits="false" boundaryCondition="false" constant="false"/>
      <species id="Ara" name="Ara" compartment="default" initialConcentration="0" substanceUnits="mole" hasOnlySubstanceUnits="false" boundaryCondition="false" constant="false"/>
      <species id="AraC" name="AraC" compartment="default" initialConcentration="0" substanceUnits="mole" hasOnlySubstanceUnits="false" boundaryCondition="false" constant="false"/>
    </listOfSpecies>
    <listOfParameters>
      <parameter id="k__" value="1" constant="true"/>
      <parameter id="K__" value="20" constant="true"/>
      <parameter id="n__" value="4" constant="true"/>
      <parameter id="kleak__" value="0.01" constant="true"/>
      <parameter id="ktl__" value="0.2" constant="true"/>
      <parameter id="kb__" value="0.05" constant="true"/>
      <parameter id="ku__" value="1" constant="true"/>
      <parameter id="kdil__" value="0.001" constant="true"/>
    </listOfParameters>
    <listOfReactions>
      <reaction id="r0" name="r0" reversible="false">
        <listOfReactants>
          <speciesReference species="dna_main_assembly" stoichiometry="1" constant="false"/>
        </listOfReactants>
        <listOfProducts>
          <speciesReference species="dna_main_assembly" stoichiometry="1" constant="false"/>
          <speciesReference species="rna_main_assembly" stoichiometry="1" constant="false"/>
        </listOfProducts>
        <listOfModifiers>
          <modifierSpeciesReference species="complex_Ara_2x_AraC_2x_"/>
        </listOfModifiers>
        <kineticLaw>
          <math xmlns="http://www.w3.org/1998/Math/MathML">
            <apply>
              <divide/>
              <apply>
                <times/>
                <ci> k__ </ci>
                <ci> dna_main_assembly </ci>
                <apply>
                  <power/>
                  <ci> complex_Ara_2x_AraC_2x_ </ci>
                  <ci> n__ </ci>
                </apply>
              </apply>
              <apply>
                <plus/>
                <apply>
                  <power/>
                  <ci> K__ </ci>
                  <ci> n__ </ci>
                </apply>
                <apply>
                  <power/>
                  <ci> complex_Ara_2x_AraC_2x_ </ci>
                  <ci> n__ </ci>
                </apply>
              </apply>
            </apply>
          </math>
        </kineticLaw>
      </reaction>
      <reaction id="r1" name="r1" reversible="false">
        <listOfReactants>
          <speciesReference species="dna_main_assembly" stoichiometry="1" constant="false"/>
        </listOfReactants>
        <listOfProducts>
          <speciesReference species="dna_main_assembly" stoichiometry="1" constant="false"/>
          <speciesReference species="rna_main_assembly" stoichiometry="1" constant="false"/>
        </listOfProducts>
        <kineticLaw>
          <math xmlns="http://www.w3.org/1998/Math/MathML">
            <apply>
              <times/>
              <ci> kleak__ </ci>
              <ci> dna_main_assembly </ci>
            </apply>
          </math>
        </kineticLaw>
      </reaction>
      <reaction id="r2" name="r2" reversible="false">
        <listOfReactants>
          <speciesReference species="rna_main_assembly" stoichiometry="1" constant="false"/>
        </listOfReactants>
        <listOfProducts>
          <speciesReference species="rna_main_assembly" stoichiometry="1" constant="false"/>
          <speciesReference species="AmtR" stoichiometry="1" constant="false"/>
        </listOfProducts>
        <kineticLaw>
          <math xmlns="http://www.w3.org/1998/Math/MathML">
            <apply>
              <times/>
              <ci> ktl__ </ci>
              <ci> rna_main_assembly </ci>
            </apply>
          </math>
        </kineticLaw>
      </reaction>
      <reaction id="r3" name="r3" reversible="false">
        <listOfReactants>
          <speciesReference species="dna_reporter_assembly" stoichiometry="1" constant="false"/>
        </listOfReactants>
        <listOfProducts>
          <speciesReference species="dna_reporter_assembly" stoichiometry="1" constant="false"/>
          <speciesReference species="rna_reporter_assembly" stoichiometry="1" constant="false"/>
        </listOfProducts>
        <listOfModifiers>
          <modifierSpeciesReference species="AmtR"/>
        </listOfModifiers>
        <kineticLaw>
          <math xmlns="http://www.w3.org/1998/Math/MathML">
            <apply>
              <divide/>
              <apply>
                <times/>
                <ci> k__ </ci>
                <ci> dna_reporter_assembly </ci>
              </apply>
              <apply>
                <plus/>
                <cn type="integer"> 1 </cn>
                <apply>
                  <power/>
                  <apply>
                    <divide/>
                    <ci> AmtR </ci>
                    <ci> K__ </ci>
                  </apply>
                  <ci> n__ </ci>
                </apply>
              </apply>
            </apply>
          </math>
        </kineticLaw>
      </reaction>
      <reaction id="r4" name="r4" reversible="false">
        <listOfReactants>
          <speciesReference species="dna_reporter_assembly" stoichiometry="1" constant="false"/>
        </listOfReactants>
        <listOfProducts>
          <speciesReference species="dna_reporter_assembly" stoichiometry="1" constant="false"/>
          <speciesReference species="rna_reporter_assembly" stoichiometry="1" constant="false"/>
        </listOfProducts>
        <kineticLaw>
          <math xmlns="http://www.w3.org/1998/Math/MathML">
            <apply>
              <times/>
              <ci> kleak__ </ci>
              <ci> dna_reporter_assembly </ci>
            </apply>
          </math>
        </kineticLaw>
      </reaction>
      <reaction id="r5" name="r5" reversible="false">
        <listOfReactants>
          <speciesReference species="rna_reporter_assembly" stoichiometry="1" constant="false"/>
        </listOfReactants>
        <listOfProducts>
          <speciesReference species="rna_reporter_assembly" stoichiometry="1" constant="false"/>
          <speciesReference species="YFP" stoichiometry="1" constant="false"/>
        </listOfProducts>
        <kineticLaw>
          <math xmlns="http://www.w3.org/1998/Math/MathML">
            <apply>
              <times/>
              <ci> ktl__ </ci>
              <ci> rna_reporter_assembly </ci>
            </apply>
          </math>
        </kineticLaw>
      </reaction>
      <reaction id="r6" name="r6" reversible="false">
        <listOfReactants>
          <speciesReference species="Ara" stoichiometry="2" constant="false"/>
          <speciesReference species="AraC" stoichiometry="2" constant="false"/>
        </listOfReactants>
        <listOfProducts>
          <speciesReference species="complex_Ara_2x_AraC_2x_" stoichiometry="1" constant="false"/>
        </listOfProducts>
        <kineticLaw>
          <math xmlns="http://www.w3.org/1998/Math/MathML">
            <apply>
              <times/>
              <ci> kb__ </ci>
              <apply>
                <power/>
                <ci> Ara </ci>
                <cn type="integer"> 2 </cn>
              </apply>
              <apply>
                <power/>
                <ci> AraC </ci>
                <cn type="integer"> 2 </cn>
              </apply>
            </apply>
          </math>
        </kineticLaw>
      </reaction>
      <reaction id="r6rev" name="r6rev" reversible="false">
        <listOfReactants>
          <speciesReference species="complex_Ara_2x_AraC_2x_" stoichiometry="1" constant="false"/>
        </listOfReactants>
        <listOfProducts>
          <speciesReference species="Ara" stoichiometry="2" constant="false"/>
          <speciesReference species="AraC" stoichiometry="2" constant="false"/>
        </listOfProducts>
        <kineticLaw>
          <math xmlns="http://www.w3.org/1998/Math/MathML">
            <apply>
              <times/>
              <ci> ku__ </ci>
              <ci> complex_Ara_2x_AraC_2x_ </ci>
            </apply>
          </math>
        </kineticLaw>
      </reaction>
      <reaction id="r7" name="r7" reversible="false">
        <listOfReactants>
          <speciesReference species="rna_main_assembly" stoichiometry="1" constant="false"/>
        </listOfReactants>
        <kineticLaw>
          <math xmlns="http://www.w3.org/1998/Math/MathML">
            <apply>
              <times/>
              <ci> kdil__ </ci>
              <ci> rna_main_assembly </ci>
            </apply>
          </math>
        </kineticLaw>
      </reaction>
      <reaction id="r8" name="r8" reversible="false">
        <listOfReactants>
          <speciesReference species="rna_reporter_assembly" stoichiometry="1" constant="false"/>
        </listOfReactants>
        <kineticLaw>
          <math xmlns="http://www.w3.org/1998/Math/MathML">
            <apply>
              <times/>
              <ci> kdil__ </ci>
              <ci> rna_reporter_assembly </ci>
            </apply>
          </math>
        </kineticLaw>
      </reaction>
    </listOfReactions>
  </model>
</sbml>
